mayek/__init__.py
mayek/main.py
mayek/mayek.json
meiteimayek_mapping-0.0.1.dist-info/METADATA
meiteimayek_mapping-0.0.1.dist-info/WHEEL
meiteimayek_mapping-0.0.1.dist-info/top_level.txt
meiteimayek_mapping-0.0.1.dist-info/RECORD
