Metadata-Version: 2.1
Name: meiteimayek-mapping
Version: 0.0.1
Summary: Utility Functions for managing Meitei Mayek Characters and mapping to E-pao Font.
Home-page: https://github.com/GyanendroKh/MayekMapping/tree/master/python
Author: Gyanendro Kh
Author-email: me@gyanendrokh.dev
License: Apache-2.0
Keywords: meiteimayek,meitei-mayek,mapping,utility,manipuri
Classifier: Development Status :: 5 - Production/Stable
Classifier: Intended Audience :: Developers
Classifier: License :: OSI Approved :: Apache Software License
Classifier: Programming Language :: Python :: 3
Classifier: Operating System :: OS Independent
